floataddingpackage/__init__.py
floataddingpackage/add.py
addtwopackage-0.1.0.dist-info/METADATA
addtwopackage-0.1.0.dist-info/WHEEL
addtwopackage-0.1.0.dist-info/top_level.txt
addtwopackage-0.1.0.dist-info/RECORD
