Metadata-Version: 2.4
Name: addtwopackage
Version: 0.1.0
Summary: A simple package to add two numbers
Author-email: Fardin <onik126.cse@gmail.com>
License: MIT
Project-URL: Homepage, https://github.com/fardin0045/addtwo
Requires-Python: >=3.7
